canvassyncer/__init__.py
canvassyncer/__main__.py
canvassyncer-2.0.12.dist-info/LICENSE
canvassyncer-2.0.12.dist-info/METADATA
canvassyncer-2.0.12.dist-info/WHEEL
canvassyncer-2.0.12.dist-info/entry_points.txt
canvassyncer-2.0.12.dist-info/top_level.txt
canvassyncer-2.0.12.dist-info/RECORD
