Metadata-Version: 2.1
Name: canvassyncer
Version: 2.0.12
Summary: The async fast canavs file syncer.
Home-page: https://github.com/BoYanZh/Canvas-Syncer
Author: SJTU JI Tech
Author-email: bomingzh@sjtu.edu.cn
Maintainer: BoYanZh
Maintainer-email: bomingzh@sjtu.edu.cn
License: MIT
Project-URL: Bug Reports, https://github.com/BoYanZh/Canvas-Syncer/issues
Project-URL: Source, https://github.com/BoYanZh/Canvas-Syncer
Requires-Python: >=3.6
License-File: LICENSE
Requires-Dist: httpx
Requires-Dist: aiofiles
Requires-Dist: tqdm
